catly_ding/__init__.py
catly_ding/__version.py
catly_ding-0.0.1.dist-info/METADATA
catly_ding-0.0.1.dist-info/WHEEL
catly_ding-0.0.1.dist-info/top_level.txt
catly_ding-0.0.1.dist-info/RECORD
